pypsamcp/__init__.py
pypsamcp/core.py
pypsamcp/server.py
pypsamcp-0.1.3.dist-info/licenses/LICENSE
pypsamcp-0.1.3.dist-info/METADATA
pypsamcp-0.1.3.dist-info/WHEEL
pypsamcp-0.1.3.dist-info/entry_points.txt
pypsamcp-0.1.3.dist-info/top_level.txt
pypsamcp-0.1.3.dist-info/RECORD
