Metadata-Version: 2.4
Name: pypsamcp
Version: 0.1.3
Summary: PyPSA MCP: PyPSA Energy Modeling for LLMs
Author-email: Carlos Gaete <cdgaete@gmail.com>
License: MIT
Project-URL: Homepage, https://github.com/cdgaete/pypsa-mcp
Project-URL: Bug Tracker, https://github.com/cdgaete/pypsa-mcp/issues
Project-URL: Source Code, https://github.com/cdgaete/pypsa-mcp
Keywords: mcp,pypsa,energy,modeling,claude,ai,assistant
Classifier: Development Status :: 4 - Beta
Classifier: Intended Audience :: Developers
Classifier: License :: OSI Approved :: MIT License
Classifier: Programming Language :: Python :: 3
Classifier: Programming Language :: Python :: 3.10
Classifier: Programming Language :: Python :: 3.11
Classifier: Programming Language :: Python :: 3.12
Classifier: Programming Language :: Python :: 3.13
Classifier: Topic :: Software Development :: Libraries :: Python Modules
Classifier: Topic :: Scientific/Engineering :: Physics
Classifier: Topic :: Utilities
Requires-Python: >=3.10
License-File: LICENSE
Requires-Dist: fastmcp>=2.2.0
Requires-Dist: pypsa>=0.33.0
Requires-Dist: pandas>=2.2.1
Requires-Dist: numpy>=2.2.1
Requires-Dist: highspy>=1.10.0
Provides-Extra: dev
Requires-Dist: pytest>=8.3.5; extra == "dev"
Requires-Dist: black>=24.3.0; extra == "dev"
Requires-Dist: ruff>=0.3.4; extra == "dev"
Requires-Dist: build>=1.2.1; extra == "dev"
Dynamic: license-file
